odoo/addons/home_background_image/LICENSE
odoo/addons/home_background_image/README.rst
odoo/addons/home_background_image/__init__.py
odoo/addons/home_background_image/__manifest__.py
odoo/addons/home_background_image/images/screen.png
odoo/addons/home_background_image/models/__init__.py
odoo/addons/home_background_image/models/res_company.py
odoo/addons/home_background_image/static/description/icon.png
odoo/addons/home_background_image/static/description/index.html
odoo/addons/home_background_image/static/src/webclient/home_menu/home_menu_background.scss
odoo/addons/home_background_image/views/base.xml
odoo_addon_home_background_image-16.0.1.0.0.dist-info/METADATA
odoo_addon_home_background_image-16.0.1.0.0.dist-info/WHEEL
odoo_addon_home_background_image-16.0.1.0.0.dist-info/top_level.txt
odoo_addon_home_background_image-16.0.1.0.0.dist-info/RECORD
